app_config/__init__.py
app_config/__version__.py
app_config/config.py
app_config/configparms.py
app_config/configparms_ext.py
app_config/configutils.py
app_config/gen_config.py
app_config-2.1.1.dist-info/licenses/LICENSE
app_config-2.1.1.dist-info/METADATA
app_config-2.1.1.dist-info/WHEEL
app_config-2.1.1.dist-info/entry_points.txt
app_config-2.1.1.dist-info/top_level.txt
app_config-2.1.1.dist-info/RECORD
