Metadata-Version: 2.4
Name: app_config
Version: 2.1.1
Summary: Read a config file and create a config module from the config variables which can be passed throughout an application. Reading and writing of the config file are based on configparser.
Author-email: Criss Swaim <cswaim@tpginc.net>
Maintainer-email: Criss Swaim <cswaim@tpginc.net>
License-Expression: Apache-2.0
Project-URL: Repository, https://gitlab.com/tpgllc/app_config
Project-URL: Customization, https://gitlab.com/tpgllc/app_config/-/blob/main/doc/customizing.md
Project-URL: Issues, https://gitlab.com/tpgllc/app_config/issues
Project-URL: Changelog, https://gitlab.com/tpgllc/app_config/-/blob/main/doc/changelog.md
Keywords: config,config file,application configuration,application configuration file,app config file
Classifier: Development Status :: 5 - Production/Stable
Classifier: Programming Language :: Python :: 3.10
Classifier: Programming Language :: Python :: 3.11
Classifier: Programming Language :: Python :: 3.12
Classifier: Programming Language :: Python :: 3.13
Classifier: Programming Language :: Python :: 3.14
Classifier: Operating System :: OS Independent
Requires-Python: >=3.10
License-File: LICENSE
Provides-Extra: dev
Requires-Dist: build>=1.2.2; extra == "dev"
Requires-Dist: twine>=6.0.1; extra == "dev"
Requires-Dist: wheel>=0.45.1; extra == "dev"
Requires-Dist: packaging>=24.2; extra == "dev"
Requires-Dist: coverage; extra == "dev"
Requires-Dist: flake8; extra == "dev"
Requires-Dist: tox; extra == "dev"
Requires-Dist: mypy>=1.5.0; extra == "dev"
Requires-Dist: pytest; extra == "dev"
Requires-Dist: pytest-cov>=4.1.0; extra == "dev"
Requires-Dist: black>=23.7.0; extra == "dev"
Requires-Dist: ruff>=0.0.287; extra == "dev"
Dynamic: license-file
